google_analytics/__init__.py
google_analytics-0.0.0.dist-info/METADATA
google_analytics-0.0.0.dist-info/WHEEL
google_analytics-0.0.0.dist-info/top_level.txt
google_analytics-0.0.0.dist-info/RECORD
